CHANGES.rst
LICENSE
MANIFEST.in
README.rst
setup.cfg
setup.py
redshift_sqlalchemy/__init__.py
sqlalchemy_redshift/__init__.py
sqlalchemy_redshift/commands.py
sqlalchemy_redshift/ddl.py
sqlalchemy_redshift/dialect.py
sqlalchemy_redshift/redshift-ca-bundle.crt
sqlalchemy_redshift_no_spectrum.egg-info/PKG-INFO
sqlalchemy_redshift_no_spectrum.egg-info/SOURCES.txt
sqlalchemy_redshift_no_spectrum.egg-info/dependency_links.txt
sqlalchemy_redshift_no_spectrum.egg-info/entry_points.txt
sqlalchemy_redshift_no_spectrum.egg-info/requires.txt
sqlalchemy_redshift_no_spectrum.egg-info/top_level.txt