Metadata-Version: 2.1
Name: sqlalchemy-redshift-no-spectrum
Version: 0.8.12
Summary: Fork of Amazon Redshift Dialect for sqlalchemy without Spectrum support
Home-page: https://github.com/preset-io/sqlalchemy-redshift
Author: Matt George
Author-email: mgeorge@gmail.com
Maintainer: Beto Dealmeida
Maintainer-email: beto@preset.io
License: MIT
Classifier: Development Status :: 4 - Beta
Classifier: Environment :: Console
Classifier: Intended Audience :: Developers
Classifier: License :: OSI Approved :: MIT License
Classifier: Operating System :: OS Independent
Classifier: Programming Language :: Python
Classifier: Programming Language :: Python :: 3
Classifier: Programming Language :: Python :: 3.4
Classifier: Programming Language :: Python :: 3.5
Classifier: Programming Language :: Python :: 3.6
Classifier: Programming Language :: Python :: 3.7
Classifier: Programming Language :: Python :: 3.8
Classifier: Programming Language :: Python :: 3.9
Requires-Python: >=3.4
License-File: LICENSE
